upgini/__about__.py
upgini/__init__.py
upgini/ads.py
upgini/dataset.py
upgini/errors.py
upgini/features_enricher.py
upgini/http.py
upgini/metadata.py
upgini/metrics.py
upgini/search_task.py
upgini/spinner.py
upgini/version_validator.py
upgini/ads_management/__init__.py
upgini/ads_management/ads_manager.py
upgini/autofe/__init__.py
upgini/autofe/all_operators.py
upgini/autofe/binary.py
upgini/autofe/date.py
upgini/autofe/feature.py
upgini/autofe/groupby.py
upgini/autofe/operator.py
upgini/autofe/unary.py
upgini/autofe/utils.py
upgini/autofe/vector.py
upgini/autofe/timeseries/__init__.py
upgini/autofe/timeseries/base.py
upgini/autofe/timeseries/cross.py
upgini/autofe/timeseries/delta.py
upgini/autofe/timeseries/lag.py
upgini/autofe/timeseries/roll.py
upgini/autofe/timeseries/trend.py
upgini/autofe/timeseries/volatility.py
upgini/data_source/__init__.py
upgini/data_source/data_source_publisher.py
upgini/mdc/__init__.py
upgini/mdc/context.py
upgini/normalizer/__init__.py
upgini/normalizer/normalize_utils.py
upgini/resource_bundle/__init__.py
upgini/resource_bundle/exceptions.py
upgini/resource_bundle/strings.properties
upgini/resource_bundle/strings_widget.properties
upgini/sampler/__init__.py
upgini/sampler/base.py
upgini/sampler/random_under_sampler.py
upgini/sampler/utils.py
upgini/utils/Roboto-Regular.ttf
upgini/utils/__init__.py
upgini/utils/base_search_key_detector.py
upgini/utils/blocked_time_series.py
upgini/utils/config.py
upgini/utils/country_utils.py
upgini/utils/custom_loss_utils.py
upgini/utils/cv_utils.py
upgini/utils/datetime_utils.py
upgini/utils/deduplicate_utils.py
upgini/utils/display_utils.py
upgini/utils/email_utils.py
upgini/utils/fallback_progress_bar.py
upgini/utils/feature_info.py
upgini/utils/features_validator.py
upgini/utils/format.py
upgini/utils/hash_utils.py
upgini/utils/ip_utils.py
upgini/utils/mstats.py
upgini/utils/one_hot_encoder.py
upgini/utils/phone_utils.py
upgini/utils/postal_code_utils.py
upgini/utils/progress_bar.py
upgini-1.2.150.dist-info/METADATA
upgini-1.2.150.dist-info/WHEEL
upgini-1.2.150.dist-info/licenses/LICENSE
upgini-1.2.150.dist-info/RECORD
