Metadata-Version: 2.4
Name: upgini
Version: 1.2.150
Summary: Intelligent data search & enrichment for Machine Learning
Project-URL: Bug Reports, https://github.com/upgini/upgini/issues
Project-URL: Homepage, https://upgini.com/
Project-URL: Source, https://github.com/upgini/upgini
Author-email: Upgini Developers <madewithlove@upgini.com>
License-File: LICENSE
Keywords: automl,data mining,data science,data search,machine learning
Classifier: Development Status :: 5 - Production/Stable
Classifier: Intended Audience :: Customer Service
Classifier: Intended Audience :: Developers
Classifier: Intended Audience :: Financial and Insurance Industry
Classifier: Intended Audience :: Information Technology
Classifier: Intended Audience :: Science/Research
Classifier: Intended Audience :: Telecommunications Industry
Classifier: License :: OSI Approved :: BSD License
Classifier: Operating System :: OS Independent
Classifier: Programming Language :: Python :: 3.10
Classifier: Programming Language :: Python :: 3.11
Classifier: Programming Language :: Python :: 3.12
Classifier: Topic :: Scientific/Engineering :: Artificial Intelligence
Classifier: Topic :: Scientific/Engineering :: Information Analysis
Requires-Python: <3.13,>=3.10
Requires-Dist: catboost>=1.0.3
Requires-Dist: category-encoders>=2.8.1
Requires-Dist: fastparquet>=0.8.1
Requires-Dist: ipywidgets>=8.1.0
Requires-Dist: jarowinkler>=2.0.0
Requires-Dist: levenshtein>=0.25.1
Requires-Dist: lightgbm>=4.6.0
Requires-Dist: more-itertools==10.7.0
Requires-Dist: numpy<3.0.0,>=1.19.0
Requires-Dist: pandas<3.0.0,>=1.1.0
Requires-Dist: psutil>=5.9.0
Requires-Dist: pyarrow==18.1.0
Requires-Dist: pydantic<3.0.0,>1.0.0
Requires-Dist: pyjwt>=2.8.0
Requires-Dist: python-bidi==0.4.2
Requires-Dist: python-dateutil>=2.8.0
Requires-Dist: python-json-logger>=3.3.0
Requires-Dist: requests>=2.8.0
Requires-Dist: scikit-learn<1.8.0,>=1.3.0
Requires-Dist: scipy>=1.10.0
Requires-Dist: shap>=0.44.0
Requires-Dist: xhtml2pdf<0.3.0,>=0.2.11
